{
  "code": {
    "fadeAnimationCode": [
      { "type": "html", "data": "<template>" },
      { "type": "html", "data": "  <div>" },
      { "type": "html", "data": "    <el-button @click=\"show = !show\">Click Me</el-button>" },
      { "type": "html", "data": "" },
      { "type": "html", "data": "    <div style=\"display: flex; margin-top: 20px; height: 100px;\">" },
      { "type": "html", "data": "      <transition name=\"el-fade-in-linear\">" },
      { "type": "html", "data": "        <div v-show=\"show\" class=\"transition-box\">.el-fade-in-linear</div>" },
      { "type": "html", "data": "      </transition>" },
      { "type": "html", "data": "" },
      { "type": "html", "data": "      <transition name=\"el-fade-in\">" },
      { "type": "html", "data": "        <div v-show=\"show\" class=\"transition-box\">.el-fade-in</div>" },
      { "type": "html", "data": "      </transition>" },
      { "type": "html", "data": "    </div>" },
      { "type": "html", "data": "  </div>" },
      { "type": "html", "data": "</template>" },
      { "type": "html", "data": "" },
      { "type": "html", "data": "<script>" },
      { "type": "js", "data": "  export default {" },
      { "type": "js", "data": "     data: () => ({" },
      { "type": "js", "data": "       show: true" },
      { "type": "js", "data": "     })" },
      { "type": "js", "data": "  }" },
      { "type": "html", "data": "</script>" },
      { "type": "html", "data": "" },
      { "type": "html", "data": "<style lang=\"scss\" scoped>" },
      { "type": "css", "data": ".transition-box {" },
      { "type": "css", "data": "  margin-bottom: 10px;" },
      { "type": "css", "data": "  width: 200px;" },
      { "type": "css", "data": "  height: 100px;" },
      { "type": "css", "data": "  border-radius: 4px;" },
      { "type": "css", "data": "  background-color: #409EFF;" },
      { "type": "css", "data": "  text-align: center;" },
      { "type": "css", "data": "  color: #ffffff;" },
      { "type": "css", "data": "  padding: 40px 20px;" },
      { "type": "css", "data": "  box-sizing: border-box;" },
      { "type": "css", "data": "  margin-right: 20px;" },
      { "type": "css", "data": "}" },
      { "type": "html", "data": "</style>" }
    ],
    "zoomAnimationCode": [
      { "type": "html", "data": "<template>" },
      { "type": "html", "data": "  <div>" },
      { "type": "html", "data": "    <el-button @click=\"show = !show\">Click Me</el-button>" },
      { "type": "html", "data": "" },
      { "type": "html", "data": "    <div style=\"display: flex; margin-top: 20px; height: 100px;\">" },
      { "type": "html", "data": "      <transition name=\"el-zoom-in-center\">" },
      { "type": "html", "data": "        <div v-show=\"show\" class=\"transition-box\">.el-zoom-in-center</div>" },
      { "type": "html", "data": "      </transition>" },
      { "type": "html", "data": "" },
      { "type": "html", "data": "      <transition name=\"el-zoom-in-top\">" },
      { "type": "html", "data": "        <div v-show=\"show\" class=\"transition-box\">.el-zoom-in-top</div>" },
      { "type": "html", "data": "      </transition>" },
      { "type": "html", "data": "" },
      { "type": "html", "data": "      <transition name=\"el-zoom-in-bottom\">" },
      { "type": "html", "data": "        <div v-show=\"show\" class=\"transition-box\">.el-zoom-in-bottom</div>" },
      { "type": "html", "data": "      </transition>" },
      { "type": "html", "data": "    </div>" },
      { "type": "html", "data": "  </div>" },
      { "type": "html", "data": "</template>" },
      { "type": "html", "data": "" },
      { "type": "html", "data": "<script>" },
      { "type": "js", "data": "  export default {" },
      { "type": "js", "data": "     data: () => ({" },
      { "type": "js", "data": "       show: true" },
      { "type": "js", "data": "     })" },
      { "type": "js", "data": "  }" },
      { "type": "html", "data": "</script>" },
      { "type": "html", "data": "" },
      { "type": "html", "data": "<style lang=\"scss\" scoped>" },
      { "type": "css", "data": ".transition-box {" },
      { "type": "css", "data": "  margin-bottom: 10px;" },
      { "type": "css", "data": "  width: 200px;" },
      { "type": "css", "data": "  height: 100px;" },
      { "type": "css", "data": "  border-radius: 4px;" },
      { "type": "css", "data": "  background-color: #409EFF;" },
      { "type": "css", "data": "  text-align: center;" },
      { "type": "css", "data": "  color: #ffffff;" },
      { "type": "css", "data": "  padding: 40px 20px;" },
      { "type": "css", "data": "  box-sizing: border-box;" },
      { "type": "css", "data": "  margin-right: 20px;" },
      { "type": "css", "data": "}" },
      { "type": "html", "data": "</style>" }
    ],
    "collapseAnimationCode": [
      { "type": "html", "data": "<template>" },
      { "type": "html", "data": "  <div>" },
      { "type": "html", "data": "    <el-button @click=\"show = !show\">Click Me</el-button>" },
      { "type": "html", "data": "" },
      { "type": "html", "data": "    <div style=\"margin-top: 20px; height: 200px;\">" },
      { "type": "html", "data": "      <collapse-transition>" },
      { "type": "html", "data": "        <div v-show=\"show\">" },
      { "type": "html", "data": "          <div class=\"transition-box\">el-collapse-transition</div>" },
      { "type": "html", "data": "          <div class=\"transition-box\">el-collapse-transition</div>" },
      { "type": "html", "data": "        </div>" },
      { "type": "html", "data": "      </collapse-transition>" },
      { "type": "html", "data": "    </div>" },
      { "type": "html", "data": "  </div>" },
      { "type": "html", "data": "</template>" },
      { "type": "html", "data": "" },
      { "type": "html", "data": "<script>" },
      { "type": "js", "data": "  import CollapseTransition from 'element-ui/lib/transitions/collapse-transition'" },
      { "type": "js", "data": "" },
      { "type": "js", "data": "  export default {" },
      { "type": "js", "data": "     components: { CollapseTransition }" },
      { "type": "js", "data": "     data: () => ({" },
      { "type": "js", "data": "       show: true" },
      { "type": "js", "data": "     })" },
      { "type": "js", "data": "  }" },
      { "type": "html", "data": "</script>" },
      { "type": "html", "data": "" },
      { "type": "html", "data": "<style lang=\"scss\" scoped>" },
      { "type": "css", "data": ".transition-box {" },
      { "type": "css", "data": "  margin-bottom: 10px;" },
      { "type": "css", "data": "  width: 200px;" },
      { "type": "css", "data": "  height: 100px;" },
      { "type": "css", "data": "  border-radius: 4px;" },
      { "type": "css", "data": "  background-color: #409EFF;" },
      { "type": "css", "data": "  text-align: center;" },
      { "type": "css", "data": "  color: #ffffff;" },
      { "type": "css", "data": "  padding: 40px 20px;" },
      { "type": "css", "data": "  box-sizing: border-box;" },
      { "type": "css", "data": "  margin-right: 20px;" },
      { "type": "css", "data": "}" },
      { "type": "html", "data": "</style>" }
    ]
  },
  "attributes": [
    {
      "parameter": "margin",
      "directions": "间距",
      "type": "Number / String",
      "optional": "—",
      "default": "0"
    }
  ]
}
