{
  "code": {
    "baseCode": [
      { "type": "html", "data": "<t-query-panel class=\"my-query-panel\">" },
      { "type": "html", "data": "  <template #querybar>" },
      { "type": "html", "data": "    <el-form-item label=\"姓名\">" },
      { "type": "html", "data": "      <el-input></el-input>" },
      { "type": "html", "data": "    </el-form-item>" },
      { "type": "html", "data": "    <el-form-item>" },
      { "type": "html", "data": "      <el-button type=\"primary\">查询</el-button>" },
      { "type": "html", "data": "    </el-form-item>" },
      { "type": "html", "data": "  </template>" },
      { "type": "html", "data": "  <div class=\"my-query-center\">内容</div>" },
      { "type": "html", "data": "  <template #footer>" },
      { "type": "html", "data": "    <div class=\"my-query-footer\">底部</div>" },
      { "type": "html", "data": "  </template>" },
      { "type": "html", "data": "</t-query-panel>" },
      { "type": "html", "data": "" },
      { "type": "html", "data": "<style lang=\"scss\" scoped>" },
      { "type": "css", "data": ".my-query {" },
      { "type": "css", "data": "  &-center {" },
      { "type": "css", "data": "    display: flex;" },
      { "type": "css", "data": "    justify-content: center;" },
      { "type": "css", "data": "    align-items: center;" },
      { "type": "css", "data": "    background-color: #e9eef3;" },
      { "type": "css", "data": "    height: 200px;" },
      { "type": "css", "data": "    color: #333333;" },
      { "type": "css", "data": "  }" },
      { "type": "css", "data": "  &-footer {" },
      { "type": "css", "data": "    display: flex;" },
      { "type": "css", "data": "    justify-content: center;" },
      { "type": "css", "data": "    align-items: center;" },
      { "type": "css", "data": "    background-color: #b3c0d1;" },
      { "type": "css", "data": "    height: 60px;" },
      { "type": "css", "data": "    color: #333333;" },
      { "type": "css", "data": "  }" },
      { "type": "css", "data": "}" },
      { "type": "html", "data": "</style>" }
    ],
    "sizeCode": [
      { "type": "html", "data": "<t-query-panel class=\"my-query-panel\" size=\"medium\">" },
      { "type": "html", "data": "  <template #querybar>" },
      { "type": "html", "data": "    <el-form-item label=\"姓名\">" },
      { "type": "html", "data": "      <el-input></el-input>" },
      { "type": "html", "data": "    </el-form-item>" },
      { "type": "html", "data": "    <el-form-item>" },
      { "type": "html", "data": "      <el-button type=\"primary\">查询</el-button>" },
      { "type": "html", "data": "    </el-form-item>" },
      { "type": "html", "data": "  </template>" },
      { "type": "html", "data": "  <div class=\"my-query-center\">内容</div>" },
      { "type": "html", "data": "  <template #footer>" },
      { "type": "html", "data": "    <div class=\"my-query-footer\">底部</div>" },
      { "type": "html", "data": "  </template>" },
      { "type": "html", "data": "</t-query-panel>" },
      { "type": "html", "data": "" },
      { "type": "html", "data": "<t-query-panel class=\"my-query-panel\">" },
      { "type": "html", "data": "  <template #querybar>" },
      { "type": "html", "data": "    <el-form-item label=\"姓名\">" },
      { "type": "html", "data": "      <el-input></el-input>" },
      { "type": "html", "data": "    </el-form-item>" },
      { "type": "html", "data": "    <el-form-item>" },
      { "type": "html", "data": "      <el-button type=\"primary\">查询</el-button>" },
      { "type": "html", "data": "    </el-form-item>" },
      { "type": "html", "data": "  </template>" },
      { "type": "html", "data": "  <div class=\"my-query-center\">内容</div>" },
      { "type": "html", "data": "  <template #footer>" },
      { "type": "html", "data": "    <div class=\"my-query-footer\">底部</div>" },
      { "type": "html", "data": "  </template>" },
      { "type": "html", "data": "</t-query-panel>" },
      { "type": "html", "data": "" },
      { "type": "html", "data": "<t-query-panel class=\"my-query-panel\" size=\"mini\">" },
      { "type": "html", "data": "  <template #querybar>" },
      { "type": "html", "data": "    <el-form-item label=\"姓名\">" },
      { "type": "html", "data": "      <el-input></el-input>" },
      { "type": "html", "data": "    </el-form-item>" },
      { "type": "html", "data": "    <el-form-item>" },
      { "type": "html", "data": "      <el-button type=\"primary\">查询</el-button>" },
      { "type": "html", "data": "    </el-form-item>" },
      { "type": "html", "data": "  </template>" },
      { "type": "html", "data": "  <div class=\"my-query-center\">内容</div>" },
      { "type": "html", "data": "  <template #footer>" },
      { "type": "html", "data": "    <div class=\"my-query-footer\">底部</div>" },
      { "type": "html", "data": "  </template>" },
      { "type": "html", "data": "</t-query-panel>" },
      { "type": "html", "data": "" },
      { "type": "html", "data": "<style lang=\"scss\" scoped>" },
      { "type": "css", "data": ".my-query {" },
      { "type": "css", "data": "  &-center {" },
      { "type": "css", "data": "    display: flex;" },
      { "type": "css", "data": "    justify-content: center;" },
      { "type": "css", "data": "    align-items: center;" },
      { "type": "css", "data": "    background-color: #e9eef3;" },
      { "type": "css", "data": "    height: 200px;" },
      { "type": "css", "data": "    color: #333333;" },
      { "type": "css", "data": "  }" },
      { "type": "css", "data": "  &-footer {" },
      { "type": "css", "data": "    display: flex;" },
      { "type": "css", "data": "    justify-content: center;" },
      { "type": "css", "data": "    align-items: center;" },
      { "type": "css", "data": "    background-color: #b3c0d1;" },
      { "type": "css", "data": "    height: 60px;" },
      { "type": "css", "data": "    color: #333333;" },
      { "type": "css", "data": "  }" },
      { "type": "css", "data": "}" },
      { "type": "html", "data": "</style>" }
    ],
    "headerCode": [
      { "type": "html", "data": "<t-query-panel class=\"my-query-panel\" height=\"300px\">" },
      { "type": "html", "data": "  <template #querybar>" },
      { "type": "html", "data": "    <el-form-item label=\"姓名\">" },
      { "type": "html", "data": "      <el-input></el-input>" },
      { "type": "html", "data": "    </el-form-item>" },
      { "type": "html", "data": "    <el-form-item>" },
      { "type": "html", "data": "      <el-button type=\"primary\">查询</el-button>" },
      { "type": "html", "data": "    </el-form-item>" },
      { "type": "html", "data": "  </template>" },
      { "type": "html", "data": "  <div class=\"my-query-center\">内容</div>" },
      { "type": "html", "data": "  <template #footer>" },
      { "type": "html", "data": "    <div class=\"my-query-footer\">底部</div>" },
      { "type": "html", "data": "  </template>" },
      { "type": "html", "data": "</t-query-panel>" },
      { "type": "html", "data": "" },
      {
        "type": "html",
        "data": "<t-query-panel class=\"my-query-panel\" body-height=\"150px\" footer-height=\"100px\">"
      },
      { "type": "html", "data": "  <template #querybar>" },
      { "type": "html", "data": "    <el-form-item label=\"姓名\">" },
      { "type": "html", "data": "      <el-input></el-input>" },
      { "type": "html", "data": "    </el-form-item>" },
      { "type": "html", "data": "    <el-form-item>" },
      { "type": "html", "data": "      <el-button type=\"primary\">查询</el-button>" },
      { "type": "html", "data": "    </el-form-item>" },
      { "type": "html", "data": "  </template>" },
      { "type": "html", "data": "  <div class=\"my-query-center\">内容</div>" },
      { "type": "html", "data": "  <template #footer>" },
      { "type": "html", "data": "    <div class=\"my-query-footer\">底部</div>" },
      { "type": "html", "data": "  </template>" },
      { "type": "html", "data": "</t-query-panel>" },
      { "type": "html", "data": "" },
      { "type": "html", "data": "<style lang=\"scss\" scoped>" },
      { "type": "css", "data": ".my-query {" },
      { "type": "css", "data": "  &-center {" },
      { "type": "css", "data": "    display: flex;" },
      { "type": "css", "data": "    justify-content: center;" },
      { "type": "css", "data": "    align-items: center;" },
      { "type": "css", "data": "    background-color: #e9eef3;" },
      { "type": "css", "data": "    height: calc(100% - 60px);" },
      { "type": "css", "data": "    color: #333333;" },
      { "type": "css", "data": "  }" },
      { "type": "css", "data": "  &-footer {" },
      { "type": "css", "data": "    display: flex;" },
      { "type": "css", "data": "    justify-content: center;" },
      { "type": "css", "data": "    align-items: center;" },
      { "type": "css", "data": "    background-color: #b3c0d1;" },
      { "type": "css", "data": "    height: 60px; // 或height：100%;" },
      { "type": "css", "data": "    color: #333333;" },
      { "type": "css", "data": "  }" },
      { "type": "css", "data": "}" },
      { "type": "html", "data": "</style>" }
    ]
  },
  "attributes": [
    {
      "parameter": "model",
      "directions": "表单数据对象",
      "type": "Object",
      "optional": "—",
      "default": "—"
    },
    {
      "parameter": "size",
      "directions": "用于控制该表单内组件的尺寸",
      "type": "String",
      "optional": "medium / small / mini",
      "default": "small"
    },
    {
      "parameter": "label-width",
      "directions": "用于控制 \"el-form-item label\" 的宽度",
      "type": "String",
      "optional": "—",
      "default": "—"
    },
    {
      "parameter": "height",
      "directions": "高度",
      "type": "String / Number",
      "optional": "—",
      "default": "—",
      "keyPoint": true
    },
    {
      "parameter": "body-height",
      "directions": "主体高度，设置了 height 时，该属性不生效。",
      "type": "String / Number",
      "optional": "—",
      "default": "—",
      "keyPoint": true
    },
    {
      "parameter": "footer-height",
      "directions": "底部高度",
      "type": "String / Number",
      "optional": "—",
      "default": "—",
      "keyPoint": true
    }
  ],
  "slots": [
    { "name": "querybar", "directions": "QueryBar 的内容" },
    { "name": "—", "directions": "主体的内容" },
    { "name": "footer", "directions": "底部面板内容" }
  ]
}
